wipac_dev_tools/__init__.py
wipac_dev_tools/argparse_tools.py
wipac_dev_tools/container_registry_tools.py
wipac_dev_tools/data_safety_tools.py
wipac_dev_tools/enviro_tools.py
wipac_dev_tools/logging_tools.py
wipac_dev_tools/mongo_jsonschema_tools.py
wipac_dev_tools/prometheus_tools.py
wipac_dev_tools/py.typed
wipac_dev_tools/semver_parser_tools.py
wipac_dev_tools/setup_tools.py
wipac_dev_tools/strtobool.py
wipac_dev_tools/timing_tools.py
wipac_dev_tools-1.17.9.dist-info/licenses/LICENSE
wipac_dev_tools-1.17.9.dist-info/METADATA
wipac_dev_tools-1.17.9.dist-info/WHEEL
wipac_dev_tools-1.17.9.dist-info/top_level.txt
wipac_dev_tools-1.17.9.dist-info/RECORD
