Metadata-Version: 2.4
Name: wipac-dev-tools
Version: 1.17.9
Summary: Common, basic, and reusable development tools
Author-email: WIPAC Developers <developers@icecube.wisc.edu>
License-Expression: MIT
Project-URL: Homepage, https://pypi.org/project/wipac-dev-tools/
Project-URL: Tracker, https://github.com/WIPACrepo/wipac-dev-tools/issues
Project-URL: Source, https://github.com/WIPACrepo/wipac-dev-tools
Keywords: WIPAC,python tools,utilities
Classifier: Programming Language :: Python :: 3.10
Classifier: Programming Language :: Python :: 3.11
Classifier: Programming Language :: Python :: 3.12
Classifier: Programming Language :: Python :: 3.13
Classifier: Programming Language :: Python :: 3.14
Requires-Python: <3.15,>=3.10
License-File: LICENSE
Requires-Dist: python-dateutil
Requires-Dist: requests
Requires-Dist: typing_extensions
Provides-Extra: semver
Requires-Dist: semantic-version; extra == "semver"
Provides-Extra: mongo
Requires-Dist: pymongo; extra == "mongo"
Provides-Extra: motor-soon-deprecated
Requires-Dist: motor; extra == "motor-soon-deprecated"
Provides-Extra: jsonschema
Requires-Dist: jsonschema; extra == "jsonschema"
Provides-Extra: prometheus
Requires-Dist: prometheus-client; extra == "prometheus"
Provides-Extra: tests
Requires-Dist: pytest; extra == "tests"
Requires-Dist: pytest-asyncio; extra == "tests"
Requires-Dist: pytest-flake8; extra == "tests"
Requires-Dist: pytest-mypy; extra == "tests"
Requires-Dist: requests; extra == "tests"
Requires-Dist: semantic-version; extra == "tests"
Provides-Extra: mypy
Requires-Dist: jsonschema; extra == "mypy"
Requires-Dist: motor; extra == "mypy"
Requires-Dist: prometheus-client; extra == "mypy"
Requires-Dist: pymongo; extra == "mypy"
Requires-Dist: pytest; extra == "mypy"
Requires-Dist: pytest-asyncio; extra == "mypy"
Requires-Dist: pytest-flake8; extra == "mypy"
Requires-Dist: pytest-mypy; extra == "mypy"
Requires-Dist: requests; extra == "mypy"
Requires-Dist: semantic-version; extra == "mypy"
Dynamic: license-file
